utcxchangelib/__init__.py
utcxchangelib/phoenixhood_api.py
utcxchangelib/service_pb2.py
utcxchangelib/service_pb2_grpc.py
utcxchangelib/xchange_client.py
utcxchangelib-0.1.0.dist-info/LICENSE
utcxchangelib-0.1.0.dist-info/METADATA
utcxchangelib-0.1.0.dist-info/WHEEL
utcxchangelib-0.1.0.dist-info/top_level.txt
utcxchangelib-0.1.0.dist-info/RECORD
