Metadata-Version: 2.2
Name: utcxchangelib
Version: 0.1.0
Summary: A client library for interacting with xchange-v3
Author: Ian Magnell
Author-email: Ian Magnell <ianmm3203@gmail.com>
Classifier: Programming Language :: Python :: 3
Classifier: License :: OSI Approved :: MIT License
Classifier: Operating System :: OS Independent
Requires-Python: >=3.6
License-File: LICENSE
Requires-Dist: setuptools>=69.0
Requires-Dist: protobuf==5.29.0
Requires-Dist: grpcio==1.71.0
Requires-Dist: flask==3.1.0
Requires-Dist: flask_sse==1.0.0
Requires-Dist: flask_cors==5.0.1
Requires-Dist: requests==2.32.3
Dynamic: author
Dynamic: requires-python
